eyepy/__init__.py
eyepy/config.py
eyepy/core/__init__.py
eyepy/core/annotations.py
eyepy/core/eyebscan.py
eyepy/core/eyeenface.py
eyepy/core/eyemeta.py
eyepy/core/eyevolume.py
eyepy/core/filter.py
eyepy/core/grids.py
eyepy/core/plotting.py
eyepy/core/utils.py
eyepy/data/__init__.py
eyepy/io/__init__.py
eyepy/io/he/__init__.py
eyepy/io/he/e2e_format.py
eyepy/io/he/e2e_reader.py
eyepy/io/he/vol_reader.py
eyepy/io/he/xml_reader.py
eyepy/io/utils.py
eyepie-0.11.3.dist-info/LICENSE
eyepie-0.11.3.dist-info/METADATA
eyepie-0.11.3.dist-info/WHEEL
eyepie-0.11.3.dist-info/RECORD
