Metadata-Version: 2.1
Name: eyepie
Version: 0.11.3
Summary: A python package to read, analyse and visualize OCT and fundus data form various sources.
Home-page: https://github.com/MedVisBonn/eyepy
License: MIT
Keywords: ophthalmology,oct,visualization,spectralis
Author: Olivier Morelle
Author-email: oli4morelle@gmail.com
Requires-Python: >=3.8,<3.11
Classifier: Development Status :: 4 - Beta
Classifier: Intended Audience :: Developers
Classifier: Intended Audience :: Healthcare Industry
Classifier: Intended Audience :: Science/Research
Classifier: License :: OSI Approved :: MIT License
Classifier: Natural Language :: English
Classifier: Operating System :: OS Independent
Classifier: Programming Language :: Python :: 3
Classifier: Programming Language :: Python :: 3.8
Classifier: Programming Language :: Python :: 3.9
Classifier: Programming Language :: Python :: 3.10
Classifier: Programming Language :: Python :: 3 :: Only
Classifier: Programming Language :: Python :: 3.8
Classifier: Topic :: Scientific/Engineering :: Image Processing
Classifier: Topic :: Scientific/Engineering :: Medical Science Apps.
Classifier: Topic :: Scientific/Engineering :: Visualization
Classifier: Topic :: Software Development :: Libraries :: Python Modules
Provides-Extra: itk
Requires-Dist: construct-typing (>=0.5.5,<0.6.0)
Requires-Dist: imagecodecs (>=2023.1.23,<2024.0.0)
Requires-Dist: imageio (>=2.25.1,<3.0.0)
Requires-Dist: itk (>=5.3.0,<6.0.0) ; extra == "itk"
Requires-Dist: matplotlib (>=3.5.1,<4.0.0)
Requires-Dist: nptyping (>=2.3.1,<3.0.0)
Requires-Dist: numpy (>=1.22.0)
Requires-Dist: oct-converter (>=0.5.6,<0.6.0)
Requires-Dist: pandas (>=1.5.3,<2.0.0)
Requires-Dist: scikit-image (==0.20.0)
Project-URL: Repository, https://github.com/MedVisBonn/eyepy
